{
  "AltLookAngle": {
    "x": 0,
    "y": 0,
    "z": 0
  },
  "Autoraise": true,
  "CardID": 585842,
  "ColorDiffuse": {
    "b": 0.71324,
    "g": 0.71324,
    "r": 0.71324
  },
  "CustomDeck": {
    "5858": {
      "BackIsHidden": true,
      "BackURL": "https://drive.google.com/uc?export=download&id=1LmTlpDnBoUKErL1zH0OAhEC7HkoemDBq",
      "FaceURL": "https://drive.google.com/uc?export=download&id=1zs4a4a6hNrVJ6CvG1Ao4W4TuXjTpDR6N",
      "NumHeight": 6,
      "NumWidth": 9,
      "Type": 0,
      "UniqueBack": true
    }
  },
  "Description": "",
  "DragSelectable": true,
  "GMNotes": "",
  "GUID": "a446ba",
  "Grid": true,
  "GridProjection": false,
  "Hands": true,
  "HideWhenFaceDown": false,
  "IgnoreFoW": false,
  "LayoutGroupSortIndex": 0,
  "Locked": false,
  "LuaScript": "",
  "LuaScriptState": "",
  "MeasureMovement": false,
  "Memo": "{\"neighborhood\":\"The Unnamable\",\"type\":\"encounter\"}",
  "Name": "Card",
  "Nickname": "",
  "SidewaysCard": false,
  "Snap": true,
  "Sticky": true,
  "Tooltip": true,
  "Transform": {
    "posX": -15.165,
    "posY": 2.297,
    "posZ": -7.646,
    "rotX": 0,
    "rotY": 180,
    "rotZ": 180,
    "scaleX": 1.5,
    "scaleY": 1,
    "scaleZ": 1.5
  },
  "Value": 0,
  "XmlUI": ""
}
