{
  "AltLookAngle": {
    "x": 0,
    "y": 0,
    "z": 0
  },
  "Autoraise": true,
  "CardID": 582309,
  "ColorDiffuse": {
    "b": 0.71324,
    "g": 0.71324,
    "r": 0.71324
  },
  "CustomDeck": {
    "5823": {
      "BackIsHidden": true,
      "BackURL": "https://steamusercontent-a.akamaihd.net/ugc/15462223440441946523/ED0C1DAC0ACD12C163CD33F2337A2E7C14177B14/",
      "FaceURL": "https://steamusercontent-a.akamaihd.net/ugc/13820711599416235942/C7280EE7A902B353D8F650C9E581392F8F932353/",
      "NumHeight": 4,
      "NumWidth": 5,
      "Type": 0,
      "UniqueBack": true
    }
  },
  "Description": "",
  "DragSelectable": true,
  "GMNotes": "",
  "GUID": "45716d",
  "Grid": true,
  "GridProjection": false,
  "Hands": true,
  "HideWhenFaceDown": false,
  "IgnoreFoW": false,
  "LayoutGroupSortIndex": 0,
  "Locked": false,
  "LuaScript": "",
  "LuaScriptState": "",
  "MeasureMovement": false,
  "Memo": "{\"number\":50,\"type\":\"codex\",\"returnToArchive\":false}",
  "Name": "Card",
  "Nickname": "50",
  "SidewaysCard": false,
  "Snap": true,
  "Sticky": true,
  "Tags": [
    "codex"
  ],
  "Tooltip": true,
  "Transform": {
    "posX": 1.459,
    "posY": 0.972,
    "posZ": -4.002,
    "rotX": 0,
    "rotY": 180,
    "rotZ": 180,
    "scaleX": 1.5,
    "scaleY": 1,
    "scaleZ": 1.5
  },
  "Value": 0,
  "XmlUI": ""
}
