{
  "AltLookAngle": {
    "x": 0,
    "y": 0,
    "z": 0
  },
  "Autoraise": true,
  "CardID": 580611,
  "ColorDiffuse": {
    "b": 0.71324,
    "g": 0.71324,
    "r": 0.71324
  },
  "CustomDeck": {
    "5806": {
      "BackIsHidden": true,
      "BackURL": "https://drive.google.com/uc?export=view\u0026id=1JB7jGMKw5mV0if5myhzAvg4Bj0NpvUD6",
      "FaceURL": "https://drive.google.com/uc?export=view\u0026id=17deQqVYfHbJg4N_iKWGps4eKfnkGmsgY",
      "NumHeight": 3,
      "NumWidth": 4,
      "Type": 0,
      "UniqueBack": true
    }
  },
  "Description": "",
  "DragSelectable": true,
  "GMNotes": "",
  "GUID": "7061f8",
  "Grid": true,
  "GridProjection": false,
  "Hands": true,
  "HideWhenFaceDown": false,
  "IgnoreFoW": false,
  "LayoutGroupSortIndex": 0,
  "Locked": false,
  "LuaScript": "",
  "LuaScriptState": "",
  "MeasureMovement": false,
  "Memo": "{\"investigator\":\"Skids O'Toole\",\"type\":\"starting\"}",
  "Name": "Card",
  "Nickname": "",
  "SidewaysCard": false,
  "Snap": true,
  "Sticky": true,
  "Tags": [
    "item_magnet"
  ],
  "Tooltip": true,
  "Transform": {
    "posX": 2.075,
    "posY": 2.05,
    "posZ": -59.803,
    "rotX": 0,
    "rotY": 180,
    "rotZ": 181,
    "scaleX": 1,
    "scaleY": 1,
    "scaleZ": 1
  },
  "Value": 0,
  "XmlUI": ""
}
