{
  "AltLookAngle": {
    "x": 0,
    "y": 0,
    "z": 0
  },
  "Autoraise": true,
  "CardID": 585634,
  "ColorDiffuse": {
    "b": 0.71324,
    "g": 0.71324,
    "r": 0.71324
  },
  "CustomDeck": {
    "5856": {
      "BackIsHidden": true,
      "BackURL": "https://steamusercontent-a.akamaihd.net/ugc/13030802856670412472/B564FD6E20D91F6ABE9DE1CCEF06AEB5D3315AFE/",
      "FaceURL": "https://steamusercontent-a.akamaihd.net/ugc/14270004210214003728/317141543E94071096001C644476C48404A3B2B9/",
      "NumHeight": 5,
      "NumWidth": 8,
      "Type": 0,
      "UniqueBack": true
    }
  },
  "Description": "",
  "DragSelectable": true,
  "GMNotes": "",
  "GUID": "209037",
  "Grid": true,
  "GridProjection": false,
  "Hands": true,
  "HideWhenFaceDown": false,
  "IgnoreFoW": false,
  "LayoutGroupSortIndex": 0,
  "Locked": false,
  "LuaScript": "",
  "LuaScriptState": "",
  "MeasureMovement": false,
  "Memo": "{\"neighborhood\":\"Innsmouth Village\",\"type\":\"encounter\"}",
  "Name": "Card",
  "Nickname": "",
  "SidewaysCard": false,
  "Snap": true,
  "Sticky": true,
  "Tooltip": true,
  "Transform": {
    "posX": -19.88,
    "posY": 2.278,
    "posZ": 5.222,
    "rotX": 0,
    "rotY": 180,
    "rotZ": 180,
    "scaleX": 1.5,
    "scaleY": 1,
    "scaleZ": 1.5
  },
  "Value": 0,
  "XmlUI": ""
}
