{
  "AltLookAngle": {
    "x": 0,
    "y": 0,
    "z": 0
  },
  "Autoraise": true,
  "CardID": 577504,
  "ColorDiffuse": {
    "b": 0.71324,
    "g": 0.71324,
    "r": 0.71324
  },
  "CustomDeck": {
    "5717": {
      "BackIsHidden": true,
      "BackURL": "https://drive.google.com/uc?export=view\u0026id=1cYMUW1dTa6xDOR3z96JQcaTuBsiUlCJF",
      "FaceURL": "https://drive.google.com/uc?export=view\u0026id=13jvMMnQy5nvguDx8AtBuS8zPcJzrGQeP",
      "NumHeight": 4,
      "NumWidth": 7,
      "Type": 0,
      "UniqueBack": false
    }
  },
  "Description": "",
  "DragSelectable": true,
  "GMNotes": "",
  "GUID": "e05d11",
  "Grid": true,
  "GridProjection": false,
  "Hands": true,
  "HideWhenFaceDown": true,
  "IgnoreFoW": false,
  "LayoutGroupSortIndex": 0,
  "Locked": false,
  "LuaScript": "",
  "LuaScriptState": "",
  "MeasureMovement": false,
  "Memo": "{\"common\":true,\"hp\":4,\"price\":4,\"type\":\"item\"}",
  "Name": "Card",
  "Nickname": "",
  "SidewaysCard": false,
  "Snap": true,
  "Sticky": true,
  "Tags": [
    "item_magnet"
  ],
  "Tooltip": true,
  "Transform": {
    "posX": 9.695,
    "posY": 2.014,
    "posZ": 57.563,
    "rotX": 0,
    "rotY": 180,
    "rotZ": 180,
    "scaleX": 1,
    "scaleY": 1,
    "scaleZ": 1
  },
  "Value": 0,
  "XmlUI": ""
}
