{
  "AltLookAngle": {
    "x": 0,
    "y": 0,
    "z": 0
  },
  "AttachedSnapPoints": [
    {
      "Position": {
        "x": -0.018,
        "y": 0.15,
        "z": 0.01
      },
      "Rotation": {
        "x": 0,
        "y": 180,
        "z": 0
      },
      "Tags": [
        "anomaly_snap"
      ]
    }
  ],
  "Autoraise": true,
  "ColorDiffuse": {
    "b": 1,
    "g": 1,
    "r": 1
  },
  "CustomMesh": {
    "CastShadows": true,
    "ColliderURL": "https://drive.google.com/uc?export=download&id=1rqYTe_FV0xnRUtAWuYfhzwKo0QmFzoXV",
    "Convex": true,
    "CustomShader": {
      "FresnelStrength": 0,
      "SpecularColor": {
        "b": 1,
        "g": 1,
        "r": 1
      },
      "SpecularIntensity": 0,
      "SpecularSharpness": 2
    },
    "DiffuseURL": "https://drive.google.com/uc?export=download\u0026id=15TI38sFqG5axRrOLsDZsJq98Bl9XANJF",
    "MaterialIndex": 3,
    "MeshURL": "https://drive.google.com/uc?export=download&id=1u4ePtlk11g85UbAVzX0xFGeg1xjE9VTX",
    "NormalURL": "",
    "TypeIndex": 0
  },
  "Description": "",
  "DragSelectable": true,
  "GMNotes": "",
  "GUID": "ec2e8f",
  "Grid": true,
  "GridProjection": false,
  "Hands": false,
  "HideWhenFaceDown": false,
  "IgnoreFoW": false,
  "LayoutGroupSortIndex": 0,
  "Locked": false,
  "LuaScript": "",
  "LuaScriptState": "",
  "MeasureMovement": false,
  "Memo": "{\"locations\":[\"Velma's Diner\",\"Hibb's Roadhouse\",\"Police Station\"],\"name\":\"Easttown\",\"startPosition\":{\"x\":-0.2107243090868,\"y\":1.00000166893005,\"z\":-0.8864626288414},\"structureType\":\"2\",\"type\":\"Neighborhood\"}",
  "Name": "Custom_Model",
  "Nickname": "Easttown",
  "Snap": true,
  "Sticky": true,
  "Tooltip": true,
  "Transform": {
    "posX": -28.992,
    "posY": 4.036,
    "posZ": 86.489,
    "rotX": 0,
    "rotY": 180,
    "rotZ": 0,
    "scaleX": 1.15,
    "scaleY": 1,
    "scaleZ": 1.15
  },
  "Value": 0,
  "XmlUI": ""
}
