{
  "AltLookAngle": {
    "x": 0,
    "y": 0,
    "z": 0
  },
  "AttachedSnapPoints": [
    {
      "Position": {
        "x": -0.018,
        "y": 0.15,
        "z": 0.01
      },
      "Rotation": {
        "x": 0,
        "y": 180,
        "z": 0
      },
      "Tags": [
        "anomaly_snap"
      ]
    }
  ],
  "Autoraise": true,
  "ColorDiffuse": {
    "b": 1,
    "g": 1,
    "r": 1
  },
  "CustomMesh": {
    "CastShadows": true,
    "ColliderURL": "file:////Users/yurii/AH/TTS assets/models/map_tile_variant_a_collider.obj",
    "Convex": true,
    "CustomShader": {
      "FresnelStrength": 0,
      "SpecularColor": {
        "b": 1,
        "g": 1,
        "r": 1
      },
      "SpecularIntensity": 0,
      "SpecularSharpness": 2
    },
    "DiffuseURL": "file:////Users/yurii/AH/TTS assets/map_tiles/en/Innsmouth Shore.jpg",
    "MaterialIndex": 3,
    "MeshURL": "file:////Users/yurii/AH/TTS assets/models/map_tile_variant_a.obj",
    "NormalURL": "",
    "TypeIndex": 0
  },
  "Description": "",
  "DragSelectable": true,
  "GMNotes": "",
  "GUID": "a5f33d",
  "Grid": true,
  "GridProjection": false,
  "Hands": false,
  "HideWhenFaceDown": false,
  "IgnoreFoW": false,
  "LayoutGroupSortIndex": 0,
  "Locked": false,
  "LuaScript": "",
  "LuaScriptState": "",
  "MeasureMovement": false,
  "Memo": "{\"locations\":[\"Marsh Refinery\",\"Falcon Point\",\"Gilman House\"],\"name\":\"Innsmouth Shore\",\"startPosition\":{\"x\":0.2782117952853441,\"y\":1.00000190734863,\"z\":-0.8864626288414},\"structureType\":\"2\",\"type\":\"Neighborhood\"}",
  "Name": "Custom_Model",
  "Nickname": "Innsmouth Shore",
  "Snap": true,
  "Sticky": true,
  "Tooltip": true,
  "Transform": {
    "posX": -86.74,
    "posY": 4.036,
    "posZ": 59.847,
    "rotX": 0,
    "rotY": 180,
    "rotZ": 0,
    "scaleX": 1.15,
    "scaleY": 1,
    "scaleZ": 1.15
  },
  "Value": 0,
  "XmlUI": ""
}
