{
  "AltLookAngle": {
    "x": 0,
    "y": 0,
    "z": 0
  },
  "AttachedSnapPoints": [
    {
      "Position": {
        "x": 0.885,
        "y": 0.211,
        "z": -1.184
      },
      "Rotation": {
        "x": 0,
        "y": 0,
        "z": 0
      },
      "Tags": [
        "doom_scenario"
      ]
    },
    {
      "Position": {
        "x": 0.599,
        "y": 0.21,
        "z": -1.184
      },
      "Rotation": {
        "x": 0,
        "y": 0,
        "z": 0
      },
      "Tags": [
        "doom_scenario"
      ]
    },
    {
      "Position": {
        "x": 0.313,
        "y": 0.21,
        "z": -1.184
      },
      "Rotation": {
        "x": 0,
        "y": 0,
        "z": 0
      },
      "Tags": [
        "doom_scenario"
      ]
    },
    {
      "Position": {
        "x": 0.027,
        "y": 0.21,
        "z": -1.184
      },
      "Rotation": {
        "x": 0,
        "y": 0,
        "z": 0
      },
      "Tags": [
        "doom_scenario"
      ]
    },
    {
      "Position": {
        "x": 0.885,
        "y": 0.21,
        "z": -0.668
      },
      "Rotation": {
        "x": 0,
        "y": 0,
        "z": 0
      },
      "Tags": [
        "doom_scenario"
      ]
    },
    {
      "Position": {
        "x": 0.599,
        "y": 0.21,
        "z": -0.668
      },
      "Rotation": {
        "x": 0,
        "y": 0,
        "z": 0
      },
      "Tags": [
        "doom_scenario"
      ]
    },
    {
      "Position": {
        "x": 0.313,
        "y": 0.21,
        "z": -0.668
      },
      "Rotation": {
        "x": 0,
        "y": 0,
        "z": 0
      },
      "Tags": [
        "doom_scenario"
      ]
    },
    {
      "Position": {
        "x": 0.027,
        "y": 0.21,
        "z": -0.668
      },
      "Rotation": {
        "x": 0,
        "y": 0,
        "z": 0
      },
      "Tags": [
        "doom_scenario"
      ]
    },
    {
      "Position": {
        "x": 0.885,
        "y": 0.21,
        "z": -0.153
      },
      "Rotation": {
        "x": 0,
        "y": 0,
        "z": 0
      },
      "Tags": [
        "doom_scenario"
      ]
    },
    {
      "Position": {
        "x": 0.599,
        "y": 0.21,
        "z": -0.153
      },
      "Rotation": {
        "x": 0,
        "y": 0,
        "z": 0
      },
      "Tags": [
        "doom_scenario"
      ]
    },
    {
      "Position": {
        "x": 0.313,
        "y": 0.21,
        "z": -0.153
      },
      "Rotation": {
        "x": 0,
        "y": 0,
        "z": 0
      },
      "Tags": [
        "doom_scenario"
      ]
    },
    {
      "Position": {
        "x": 0.027,
        "y": 0.209,
        "z": -0.153
      },
      "Rotation": {
        "x": 0,
        "y": 0,
        "z": 0
      },
      "Tags": [
        "doom_scenario"
      ]
    },
    {
      "Position": {
        "x": 0.879,
        "y": 0.21,
        "z": 1.229
      },
      "Rotation": {
        "x": 0,
        "y": 0,
        "z": 0
      },
      "Tags": [
        "clue_scenario"
      ]
    },
    {
      "Position": {
        "x": 0.593,
        "y": 0.21,
        "z": 1.229
      },
      "Rotation": {
        "x": 0,
        "y": 0,
        "z": 0
      },
      "Tags": [
        "clue_scenario"
      ]
    },
    {
      "Position": {
        "x": 0.307,
        "y": 0.21,
        "z": 1.229
      },
      "Rotation": {
        "x": 0,
        "y": 0,
        "z": 0
      },
      "Tags": [
        "clue_scenario"
      ]
    },
    {
      "Position": {
        "x": 0.021,
        "y": 0.21,
        "z": 1.229
      },
      "Rotation": {
        "x": 0,
        "y": 0,
        "z": 0
      },
      "Tags": [
        "clue_scenario"
      ]
    },
    {
      "Position": {
        "x": 0.879,
        "y": 0.21,
        "z": 0.714
      },
      "Rotation": {
        "x": 0,
        "y": 0,
        "z": 0
      },
      "Tags": [
        "clue_scenario"
      ]
    },
    {
      "Position": {
        "x": 0.593,
        "y": 0.21,
        "z": 0.714
      },
      "Rotation": {
        "x": 0,
        "y": 0,
        "z": 0
      },
      "Tags": [
        "clue_scenario"
      ]
    },
    {
      "Position": {
        "x": 0.307,
        "y": 0.21,
        "z": 0.714
      },
      "Rotation": {
        "x": 0,
        "y": 0,
        "z": 0
      },
      "Tags": [
        "clue_scenario"
      ]
    },
    {
      "Position": {
        "x": 0.021,
        "y": 0.21,
        "z": 0.714
      },
      "Rotation": {
        "x": 0,
        "y": 0,
        "z": 0
      },
      "Tags": [
        "clue_scenario"
      ]
    }
  ],
  "Autoraise": true,
  "CardID": 586701,
  "ColorDiffuse": {
    "b": 0.71324,
    "g": 0.71324,
    "r": 0.71324
  },
  "CustomDeck": {
    "5867": {
      "BackIsHidden": true,
      "BackURL": "https://drive.google.com/uc?export=download\u0026id=1RgMawIwHqnT_sCbqACCl8pGBsj-BfKN9",
      "FaceURL": "https://drive.google.com/uc?export=download\u0026id=15Bu3jm6xxnFOwaWLST8hakcbVZNXok5B",
      "NumHeight": 2,
      "NumWidth": 2,
      "Type": 1,
      "UniqueBack": true
    }
  },
  "Description": "",
  "DragSelectable": true,
  "GMNotes": "",
  "GUID": "e024fc",
  "Grid": true,
  "GridProjection": false,
  "Hands": true,
  "HideWhenFaceDown": false,
  "IgnoreFoW": false,
  "LayoutGroupSortIndex": 0,
  "Locked": false,
  "LuaScript": "",
  "LuaScriptState": "",
  "MeasureMovement": false,
  "Memo": "{\"archive\":[138,139,140,141,142,143,144,145,146,147,148,149],\"codex\":[1,135,136,137],\"monsterdeck\":[\"Abyssal Servant\",\"Coursing Hound\",\"Flesh-eater\",\"Flesh-eater\",\"Nightmarish Fiend\",\"Swift Byakhee\",\"Tunneling Dhole\",\"Vicious Glutton\",\"Vicious Glutton\",\"Troubled Spirit\",\"gug\",\"ghast\"],\"monsterspawn\":{\"Vicious Glutton\":[{\"location\":\"Southside\",\"position\":{\"x\":3.316,\"y\":0.164,\"z\":-0.457},\"rotation\":{\"x\":0,\"y\":180,\"z\":180}}],\"Taloned Cannibal\":[{\"location\":\"French Hill\",\"position\":{\"x\":-1.688,\"y\":0.164,\"z\":-3.051},\"rotation\":{\"x\":0,\"y\":180,\"z\":180}}]},\"allyspawn\":[{\"source\":{\"boardMemo\":{\"type\":\"ShopMat\"},\"deckType\":\"ally\"},\"targets\":[{\"location\":\"Miskatonic University\",\"position\":{\"x\":3.919,\"y\":0.164,\"z\":1.896},\"rotation\":{\"x\":0,\"y\":180,\"z\":180}},{\"location\":\"Uptown\",\"position\":{\"x\":-3.209,\"y\":0.164,\"z\":2.01},\"rotation\":{\"x\":0,\"y\":180,\"z\":180}},{\"location\":\"French Hill\",\"position\":{\"x\":3.919,\"y\":0.164,\"z\":1.896},\"rotation\":{\"x\":0,\"y\":180,\"z\":180}}]}],\"mythosCups\":{\"Blank\":2,\"Gate Burst\":1,\"Read Headline\":2,\"Reckoning\":1,\"Spawn Clue\":2,\"Spawn Monster\":2,\"Spread Doom\":4},\"name\":\"TDCO\",\"number\":12,\"startPosition\":{\"x\":0.769335031509399,\"y\":1.01360654830933,\"z\":0.1500194411253929},\"tiles\":{\"Neighborhood\":{\"The Underworld\":{\"position\":{\"x\":0,\"y\":0.4,\"z\":0},\"rotation\":{\"x\":0,\"y\":180,\"z\":0},\"tokens\":[{\"position\":[-0.232,0.149,1.958],\"type\":\"Doom Token\"}]},\"French Hill\":{\"position\":{\"x\":-0.437,\"y\":0.4,\"z\":0},\"rotation\":{\"x\":0,\"y\":180,\"z\":0},\"tokens\":[{\"position\":[0.349,0.149,1.911],\"type\":\"Doom Token\"}]},\"Uptown\":{\"position\":{\"x\":0.22,\"y\":0.4,\"z\":0.378},\"rotation\":{\"x\":0,\"y\":180,\"z\":0},\"tokens\":[{\"position\":[-0.232,0.149,1.958],\"type\":\"Doom Token\"}]},\"Miskatonic University\":{\"position\":{\"x\":0.436,\"y\":0.4,\"z\":0},\"rotation\":{\"x\":0,\"y\":180,\"z\":0},\"tokens\":[{\"position\":[1.409,0.149,-1.453],\"type\":\"Doom Token\"}]},\"Southside\":{\"position\":{\"x\":-0.217,\"y\":0.4,\"z\":0.378},\"rotation\":{\"x\":0,\"y\":180,\"z\":0},\"tokens\":[{\"position\":[-2.028,0.149,0.56],\"type\":\"Doom Token\"}]},\"Northside\":{\"position\":{\"x\":0.22,\"y\":0.4,\"z\":-0.378},\"rotation\":{\"x\":0,\"y\":180,\"z\":0},\"tokens\":[{\"position\":[0.361,0.149,2.079],\"type\":\"Doom Token\"}]},\"Easttown\":{\"position\":{\"x\":-0.217,\"y\":0.4,\"z\":-0.378},\"rotation\":{\"x\":0,\"y\":180,\"z\":0},\"tokens\":[{\"position\":[-0.303,0.149,1.934],\"type\":\"Doom Token\"}]}},\"Street\":{\"Bridge1\":{\"position\":{\"x\":0.326,\"y\":0.2,\"z\":-0.189},\"rotation\":{\"x\":0,\"y\":120,\"z\":0}},\"Bridge2\":{\"position\":{\"x\":-0.328,\"y\":0.2,\"z\":-0.189},\"rotation\":{\"x\":0,\"y\":240,\"z\":0}},\"Residential2\":{\"position\":{\"x\":0.002,\"y\":0.2,\"z\":-0.378},\"rotation\":{\"x\":0,\"y\":180,\"z\":0}},\"Scenic2\":{\"position\":{\"x\":-0.329,\"y\":0.2,\"z\":0.189},\"rotation\":{\"x\":0,\"y\":120,\"z\":0}},\"Residential1\":{\"position\":{\"x\":0.002,\"y\":0.2,\"z\":0.378},\"rotation\":{\"x\":0,\"y\":180,\"z\":0}},\"Scenic1\":{\"position\":{\"x\":0.328,\"y\":0.2,\"z\":0.189},\"rotation\":{\"x\":0,\"y\":240,\"z\":0}}},\"Threshold\":{\"Derelict Portal\":{\"position\":{\"x\":0.11,\"y\":0.2,\"z\":0.189},\"rotation\":{\"x\":0,\"y\":120,\"z\":0}},\"Hidden Path\":{\"position\":{\"x\":0,\"y\":0.2,\"z\":-0.25},\"rotation\":{\"x\":0,\"y\":180,\"z\":0}}}},\"type\":\"Scenario\"}",
  "Name": "Card",
  "Nickname": "TDCO",
  "SidewaysCard": false,
  "Snap": true,
  "Sticky": true,
  "Tags": [
    "scenario_mat"
  ],
  "Tooltip": true,
  "Transform": {
    "posX": -32.673,
    "posY": 4.075,
    "posZ": 72.066,
    "rotX": 0,
    "rotY": 180,
    "rotZ": 0,
    "scaleX": 2.5,
    "scaleY": 1,
    "scaleZ": 2.5
  },
  "Value": 0,
  "XmlUI": ""
}
