{
  "AltLookAngle": {
    "x": 0,
    "y": 0,
    "z": 0
  },
  "Autoraise": true,
  "ColorDiffuse": {
    "b": 0.71324,
    "g": 0.71324,
    "r": 0.71324
  },
  "ContainedObjects_order": [
    "Аквінна.f905ac",
    "Дух-Провідник.3fe467",
    "МайклЛі.54aa66",
    "ПочорнілийАтаме.f4b1bb",
    "КнигаТемряви.f65dc3",
    "ХтонічнийКамінь.73584d",
    "ХимерніЕскізи.38221a",
    "МолотЦиклопа.17ef99",
    "ЗагубленийЩоденник.ad4f06",
    "ДевяткаЖезлів.3ab345",
    "ВерховнийЖрець.a0fe2d",
    "ЧервонийГодинник.c3c702",
    "ПослугаТаксиста.f24c31",
    "ПрихованіШляхи.ad1512",
    "ДоступдоСвятилища.68ca78",
    "ХранительОрдену.504c88",
    "ТаємнаЛітургія.27ce07"
  ],
  "ContainedObjects_path": "special4.7599b1",
  "CustomDeck": {
    "5869": {
      "BackIsHidden": true,
      "BackURL": "https://steamusercontent-a.akamaihd.net/ugc/13132441143517241437/E15F4FFA65B7DF11B499FE2A04D2B839F3DB613A/",
      "FaceURL": "https://steamusercontent-a.akamaihd.net/ugc/10493915626135035886/3AD4BF2223B5BBA1B0615DB14DD8163BA7396F21/",
      "NumHeight": 3,
      "NumWidth": 6,
      "Type": 0,
      "UniqueBack": false
    }
  },
  "DeckIDs": [
    586900,
    586901,
    586902,
    586903,
    586904,
    586905,
    586906,
    586907,
    586908,
    586909,
    586910,
    586911,
    586912,
    586913,
    586914,
    586915,
    586916
  ],
  "Description": "",
  "DragSelectable": true,
  "GMNotes": "",
  "GUID": "7599b1",
  "Grid": true,
  "GridProjection": false,
  "Hands": false,
  "HideWhenFaceDown": true,
  "IgnoreFoW": false,
  "LayoutGroupSortIndex": 0,
  "Locked": false,
  "LuaScript": "",
  "LuaScriptState": "",
  "MeasureMovement": false,
  "Memo": "{\"set\":3,\"startPosition\":{\"x\":0.75271475315094,\"y\":1.15572547912598,\"z\":-0.475197437524796},\"type\":\"special\"}",
  "Name": "DeckCustom",
  "Nickname": "special 4",
  "SidewaysCard": false,
  "Snap": true,
  "Sticky": true,
  "Tooltip": true,
  "Transform": {
    "posX": -12.93,
    "posY": 4.139,
    "posZ": 86.681,
    "rotX": 0,
    "rotY": 180,
    "rotZ": 180,
    "scaleX": 1,
    "scaleY": 1,
    "scaleZ": 1
  },
  "Value": 0,
  "XmlUI": ""
}
