{
  "AltLookAngle": {
    "x": 0,
    "y": 0,
    "z": 0
  },
  "Autoraise": true,
  "CardID": 586912,
  "ColorDiffuse": {
    "b": 0.71324,
    "g": 0.71324,
    "r": 0.71324
  },
  "Description": "",
  "DragSelectable": true,
  "GMNotes": "",
  "GUID": "f24c31",
  "Grid": true,
  "GridProjection": false,
  "Hands": true,
  "IgnoreFoW": false,
  "LayoutGroupSortIndex": 0,
  "Locked": false,
  "LuaScript": "",
  "LuaScriptState": "",
  "MeasureMovement": false,
  "Memo": "{\"name\":\"Cabbie's Favor\",\"type\":\"special\"}",
  "Name": "Card",
  "Nickname": "Послуга Таксиста",
  "SidewaysCard": false,
  "Snap": true,
  "Sticky": true,
  "Tags": [
    "item_magnet"
  ],
  "Tooltip": true,
  "Transform": {
    "posX": 5.428,
    "posY": 3.42,
    "posZ": 25.419,
    "rotX": 0,
    "rotY": 180,
    "rotZ": 180,
    "scaleX": 1,
    "scaleY": 1,
    "scaleZ": 1
  },
  "Value": 0,
  "XmlUI": ""
}
